{
  "openapi": "3.0.0",
  "info": {
    "title": "AIML API",
    "version": "1.0.0"
  },
  "servers": [
    {
      "url": "https://api.aimlapi.com"
    }
  ],
  "paths": {
    "/v1/batches/cancel/{batch_id}": {
      "post": {
        "operationId": "_v1_batches_cancel_batch_id",
        "parameters": [
          {
            "name": "batch_id",
            "in": "path",
            "required": true,
            "schema": {
              "type": "string"
            },
            "description": "The ID of the batch to cancel."
          }
        ],
        "responses": {
          "200": {
            "content": {
              "application/json": {
                "schema": {
                  "type": "object",
                  "properties": {
                    "id": {
                      "type": "string",
                      "description": "Unique identifier of the batch.",
                      "example": "fe91QH0tkQwaJSXo0q77O"
                    },
                    "status": {
                      "type": "string",
                      "description": "Final status of the batch after cancellation.",
                      "example": "cancelled"
                    },
                    "output": {
                      "nullable": true,
                      "description": "Batch output, if available.",
                      "example": null
                    },
                    "usage": {
                      "type": "array",
                      "description": "Usage details for the batch.",
                      "items": {
                        "type": "object"
                      },
                      "example": []
                    }
                  },
                  "required": [
                    "id",
                    "status",
                    "output",
                    "usage"
                  ]
                }
              }
            }
          }
        }
      }
    }
  }
}